.gitignore
Auto copy with QB.md
AutoPlex.md
README.md
README_en.md
plex_notify.sh
pyproject.toml
qb自动入库.md
rcp.sh
requirements.txt
setup.cfg
setup.py
tp.py
刮削攻略.md
.github/workflows/pypipublish.yml
tests/test_parseTorName.py
torcp/DeleteEmptyFolders.py
torcp/__init__.py
torcp/cacheman.py
torcp/doubanapi.py
torcp/tmdbparser.py
torcp/torcategory.py
torcp/torcp.py
torcp/tortitle.py
torcp/version.py
torcp.egg-info/PKG-INFO
torcp.egg-info/SOURCES.txt
torcp.egg-info/dependency_links.txt
torcp.egg-info/entry_points.txt
torcp.egg-info/not-zip-safe
torcp.egg-info/requires.txt
torcp.egg-info/top_level.txt