Metadata-Version: 2.1
Name: torcp
Version: 0.69
Summary: A script to rename and copy downloaded files to a target in Emby-happy way
Home-page: https://github.com/ccf-2012/torcp
Author: ccf2012
License: UNKNOWN
Project-URL: Documentation, https://github.com/ccf-2012/torcp/blob/main/README.md
Project-URL: Source, https://github.com/ccf-2012/torcp
Project-URL: Tracker, https://github.com/ccf-2012/torcp/issues
Platform: UNKNOWN
Classifier: Environment :: Console
Classifier: Operating System :: MacOS
Classifier: Operating System :: POSIX :: Linux
Classifier: Operating System :: Microsoft :: Windows
Classifier: Operating System :: OS Independent
Classifier: Programming Language :: Python :: 3.6
Classifier: Programming Language :: Python :: 3.7
Classifier: Programming Language :: Python :: 3.8
Classifier: Programming Language :: Python :: 3.9
Requires-Python: >=3.6
Provides-Extra: test
Provides-Extra: all
